setup.cfg
setup.py
website_status/__init__.py
website_status/main.py
website_up.egg-info/PKG-INFO
website_up.egg-info/SOURCES.txt
website_up.egg-info/dependency_links.txt
website_up.egg-info/entry_points.txt
website_up.egg-info/requires.txt
website_up.egg-info/top_level.txt