Metadata-Version: 1.0
Name: website-up
Version: 0.1.0.1
Summary: Check if a website is up or not
Home-page: https://github.com/prabhakar267/website-status-cli
Author: Prabhakar Gupta
Author-email: prabhakargupta267@gmail.com
License: MIT
Keywords: website-status website status status_code code
Platform: UNKNOWN
